naturaldsl/__init__.py
naturaldsl/interpreter.py
naturaldsl-0.3.0.dist-info/METADATA
naturaldsl-0.3.0.dist-info/WHEEL
naturaldsl-0.3.0.dist-info/entry_points.txt
naturaldsl-0.3.0.dist-info/top_level.txt
naturaldsl-0.3.0.dist-info/RECORD
