Metadata-Version: 2.4
Name: naturaldsl
Version: 0.3.0
Summary: A human-first natural language programming language for data science
Home-page: https://github.com/pradumana/Naturaldsl
Author: Praduman Sharma
Author-email: Praduman Sharma <prdmn.shrm@gmail.com>
License: MIT
Requires-Python: >=3.7
Requires-Dist: dask[complete]
Requires-Dist: seaborn
Requires-Dist: matplotlib
Requires-Dist: pandas
Requires-Dist: numpy
Dynamic: author
Dynamic: home-page
Dynamic: requires-python
